keyrings/kognic/proxy_auth.py
kognic_keyring-1.0.0.dist-info/METADATA
kognic_keyring-1.0.0.dist-info/WHEEL
kognic_keyring-1.0.0.dist-info/entry_points.txt
kognic_keyring-1.0.0.dist-info/top_level.txt
kognic_keyring-1.0.0.dist-info/RECORD
